keycloak_admin_client/models.py
keycloak_admin_client-26.2.4.dist-info/METADATA
keycloak_admin_client-26.2.4.dist-info/WHEEL
keycloak_admin_client-26.2.4.dist-info/RECORD
