Metadata-Version: 2.1
Name: keycloak-admin-client
Version: 26.2.4
Summary: Keycloak IAM Admin Pydantic Models
License: MIT
Author: Akshay Ranjan
Author-email: akshay.ranjan@gmail.com
Requires-Python: >=3.10,<4.0
Classifier: License :: OSI Approved :: MIT License
Classifier: Programming Language :: Python :: 3
Classifier: Programming Language :: Python :: 3.10
Classifier: Programming Language :: Python :: 3.11
Classifier: Programming Language :: Python :: 3.12
